{
  "name": "Cambermast Web",
  "image": "mcr.microsoft.com/devcontainers/javascript-node:20",
  "workspaceFolder": "/workspaces/${localWorkspaceFolderBasename}",
  "workspaceMount": "source=${localWorkspaceFolder},target=/workspaces/${localWorkspaceFolderBasename},type=bind",

  "postCreateCommand": "cd web && npm ci",

  "forwardPorts": [5173],
  "customizations": {
    "vscode": {
      "extensions": [
        "svelte.svelte-vscode",
        "esbenp.prettier-vscode",
        "dbaeumer.vscode-eslint",
        "bradlc.vscode-tailwindcss"
      ]
    }
  }
}
